stackmod/__init__.py
stackmod-0.0.6.dist-info/LICENSE
stackmod-0.0.6.dist-info/METADATA
stackmod-0.0.6.dist-info/WHEEL
stackmod-0.0.6.dist-info/top_level.txt
stackmod-0.0.6.dist-info/RECORD
