Metadata-Version: 2.1
Name: stackmod
Version: 0.0.6
Summary: Stacking for machine learning
Home-page: https://github.com/Midriaz/stackmod
Author: Midriaz
Author-email: scome@inbox.ru
License: UNKNOWN
Platform: UNKNOWN
Requires-Python: >=3.6
